{
  "clientes" : [ {
    "idCliente" : 1,
    "nome" : "Carlos",
    "endereco" : "Rua A",
    "telefone" : "111111",
    "email" : "carlos@gmail",
    "cpf" : 333
  }, {
    "idCliente" : 2,
    "nome" : "Ana",
    "endereco" : "Rua B",
    "telefone" : "2222222",
    "email" : "ana@gmail",
    "cpf" : 111
  }, {
    "idCliente" : 3,
    "nome" : "Bruno",
    "endereco" : "Rua C",
    "telefone" : "3333333",
    "email" : "bruno@gmail",
    "cpf" : 222
  }, {
    "idCliente" : 4,
    "nome" : "Carlos",
    "endereco" : "Rua A",
    "telefone" : "111111",
    "email" : "carlos@gmail",
    "cpf" : 333
  }, {
    "idCliente" : 5,
    "nome" : "Carlos",
    "endereco" : "Rua A",
    "telefone" : "111111",
    "email" : "carlos@gmail",
    "cpf" : 333
  }, {
    "idCliente" : 6,
    "nome" : "Ana",
    "endereco" : "Rua B",
    "telefone" : "2222222",
    "email" : "ana@gmail",
    "cpf" : 111
  }, {
    "idCliente" : 7,
    "nome" : "Bruno",
    "endereco" : "Rua C",
    "telefone" : "3333333",
    "email" : "bruno@gmail",
    "cpf" : 222
  }, {
    "idCliente" : 8,
    "nome" : "Carlos",
    "endereco" : "Rua A",
    "telefone" : "111111",
    "email" : "carlos@gmail",
    "cpf" : 333
  }, {
    "idCliente" : 9,
    "nome" : "Ana",
    "endereco" : "Rua B",
    "telefone" : "2222222",
    "email" : "ana@gmail",
    "cpf" : 111
  }, {
    "idCliente" : 10,
    "nome" : "Bruno",
    "endereco" : "Rua C",
    "telefone" : "3333333",
    "email" : "bruno@gmail",
    "cpf" : 222
  }, {
    "idCliente" : 11,
    "nome" : "Carlos",
    "endereco" : "Rua A",
    "telefone" : "111111",
    "email" : "carlos@gmail",
    "cpf" : 333
  }, {
    "idCliente" : 12,
    "nome" : "Carlos",
    "endereco" : "Rua A",
    "telefone" : "111111",
    "email" : "carlos@gmail",
    "cpf" : 333
  }, {
    "idCliente" : 13,
    "nome" : "Ana",
    "endereco" : "Rua B",
    "telefone" : "2222222",
    "email" : "ana@gmail",
    "cpf" : 111
  }, {
    "idCliente" : 14,
    "nome" : "Bruno",
    "endereco" : "Rua C",
    "telefone" : "3333333",
    "email" : "bruno@gmail",
    "cpf" : 222
  }, {
    "idCliente" : 15,
    "nome" : "Carlos",
    "endereco" : "Rua A",
    "telefone" : "111111",
    "email" : "carlos@gmail",
    "cpf" : 333
  }, {
    "idCliente" : 16,
    "nome" : "Ana",
    "endereco" : "Rua B",
    "telefone" : "2222222",
    "email" : "ana@gmail",
    "cpf" : 111
  }, {
    "idCliente" : 17,
    "nome" : "Bruno",
    "endereco" : "Rua C",
    "telefone" : "3333333",
    "email" : "bruno@gmail",
    "cpf" : 222
  }, {
    "idCliente" : 18,
    "nome" : "Joao",
    "endereco" : "Rua D",
    "telefone" : "4444444",
    "email" : "joao@gmail",
    "cpf" : 444
  }, {
    "idCliente" : 19,
    "nome" : "Carlos",
    "endereco" : "Rua A",
    "telefone" : "111111",
    "email" : "carlos@gmail",
    "cpf" : 333
  }, {
    "idCliente" : 20,
    "nome" : "Ana",
    "endereco" : "Rua B",
    "telefone" : "2222222",
    "email" : "ana@gmail",
    "cpf" : 111
  }, {
    "idCliente" : 21,
    "nome" : "Bruno",
    "endereco" : "Rua C",
    "telefone" : "3333333",
    "email" : "bruno@gmail",
    "cpf" : 222
  }, {
    "idCliente" : 22,
    "nome" : "Carlos",
    "endereco" : "Rua A",
    "telefone" : "111111",
    "email" : "carlos@gmail",
    "cpf" : 333
  }, {
    "idCliente" : 23,
    "nome" : "Ana",
    "endereco" : "Rua B",
    "telefone" : "2222222",
    "email" : "ana@gmail",
    "cpf" : 111
  }, {
    "idCliente" : 24,
    "nome" : "Bruno",
    "endereco" : "Rua C",
    "telefone" : "3333333",
    "email" : "bruno@gmail",
    "cpf" : 222
  }, {
    "idCliente" : 25,
    "nome" : "Carlos",
    "endereco" : "Rua A",
    "telefone" : "111111",
    "email" : "carlos@gmail",
    "cpf" : 333
  }, {
    "idCliente" : 26,
    "nome" : "Ana",
    "endereco" : "Rua B",
    "telefone" : "2222222",
    "email" : "ana@gmail",
    "cpf" : 111
  }, {
    "idCliente" : 27,
    "nome" : "Bruno",
    "endereco" : "Rua C",
    "telefone" : "3333333",
    "email" : "bruno@gmail",
    "cpf" : 222
  }, {
    "idCliente" : 28,
    "nome" : "Carlos",
    "endereco" : "Rua A",
    "telefone" : "111111",
    "email" : "carlos@gmail",
    "cpf" : 333
  }, {
    "idCliente" : 29,
    "nome" : "Ana",
    "endereco" : "Rua B",
    "telefone" : "2222222",
    "email" : "ana@gmail",
    "cpf" : 111
  }, {
    "idCliente" : 30,
    "nome" : "Bruno",
    "endereco" : "Rua C",
    "telefone" : "3333333",
    "email" : "bruno@gmail",
    "cpf" : 222
  }, {
    "idCliente" : 31,
    "nome" : "Carlos",
    "endereco" : "Rua A",
    "telefone" : "111111",
    "email" : "carlos@gmail",
    "cpf" : 333
  }, {
    "idCliente" : 32,
    "nome" : "Ana",
    "endereco" : "Rua B",
    "telefone" : "2222222",
    "email" : "ana@gmail",
    "cpf" : 111
  }, {
    "idCliente" : 33,
    "nome" : "Bruno",
    "endereco" : "Rua C",
    "telefone" : "3333333",
    "email" : "bruno@gmail",
    "cpf" : 222
  }, {
    "idCliente" : 34,
    "nome" : "Carlos",
    "endereco" : "Rua A",
    "telefone" : "111111",
    "email" : "carlos@gmail",
    "cpf" : 333
  }, {
    "idCliente" : 35,
    "nome" : "Ana",
    "endereco" : "Rua B",
    "telefone" : "2222222",
    "email" : "ana@gmail",
    "cpf" : 111
  }, {
    "idCliente" : 36,
    "nome" : "Bruno",
    "endereco" : "Rua C",
    "telefone" : "3333333",
    "email" : "bruno@gmail",
    "cpf" : 222
  }, {
    "idCliente" : 37,
    "nome" : "Carlos",
    "endereco" : "Rua A",
    "telefone" : "111111",
    "email" : "carlos@gmail",
    "cpf" : 333
  }, {
    "idCliente" : 38,
    "nome" : "Ana",
    "endereco" : "Rua B",
    "telefone" : "2222222",
    "email" : "ana@gmail",
    "cpf" : 111
  }, {
    "idCliente" : 39,
    "nome" : "Bruno",
    "endereco" : "Rua C",
    "telefone" : "3333333",
    "email" : "bruno@gmail",
    "cpf" : 222
  }, {
    "idCliente" : 40,
    "nome" : "Carlos",
    "endereco" : "Rua A",
    "telefone" : "111111",
    "email" : "carlos@gmail",
    "cpf" : 333
  }, {
    "idCliente" : 41,
    "nome" : "Ana",
    "endereco" : "Rua B",
    "telefone" : "2222222",
    "email" : "ana@gmail",
    "cpf" : 111
  }, {
    "idCliente" : 42,
    "nome" : "Bruno",
    "endereco" : "Rua C",
    "telefone" : "3333333",
    "email" : "bruno@gmail",
    "cpf" : 222
  }, {
    "idCliente" : 43,
    "nome" : "Carlos",
    "endereco" : "Rua A",
    "telefone" : "111111",
    "email" : "carlos@gmail",
    "cpf" : 333
  }, {
    "idCliente" : 44,
    "nome" : "Ana",
    "endereco" : "Rua B",
    "telefone" : "2222222",
    "email" : "ana@gmail",
    "cpf" : 111
  }, {
    "idCliente" : 45,
    "nome" : "Bruno",
    "endereco" : "Rua C",
    "telefone" : "3333333",
    "email" : "bruno@gmail",
    "cpf" : 222
  }, {
    "idCliente" : 46,
    "nome" : "Carlos",
    "endereco" : "Rua A",
    "telefone" : "111111",
    "email" : "carlos@gmail",
    "cpf" : 333
  }, {
    "idCliente" : 47,
    "nome" : "Ana",
    "endereco" : "Rua B",
    "telefone" : "2222222",
    "email" : "ana@gmail",
    "cpf" : 111
  }, {
    "idCliente" : 48,
    "nome" : "Bruno",
    "endereco" : "Rua C",
    "telefone" : "3333333",
    "email" : "bruno@gmail",
    "cpf" : 222
  }, {
    "idCliente" : 49,
    "nome" : "Carlos",
    "endereco" : "Rua A",
    "telefone" : "111111",
    "email" : "carlos@gmail",
    "cpf" : 333
  }, {
    "idCliente" : 50,
    "nome" : "Ana",
    "endereco" : "Rua B",
    "telefone" : "2222222",
    "email" : "ana@gmail",
    "cpf" : 111
  }, {
    "idCliente" : 51,
    "nome" : "Bruno",
    "endereco" : "Rua C",
    "telefone" : "3333333",
    "email" : "bruno@gmail",
    "cpf" : 222
  }, {
    "idCliente" : 52,
    "nome" : "Carlos",
    "endereco" : "Rua A",
    "telefone" : "111111",
    "email" : "carlos@gmail",
    "cpf" : 333
  }, {
    "idCliente" : 53,
    "nome" : "Ana",
    "endereco" : "Rua B",
    "telefone" : "2222222",
    "email" : "ana@gmail",
    "cpf" : 111
  }, {
    "idCliente" : 54,
    "nome" : "Bruno",
    "endereco" : "Rua C",
    "telefone" : "3333333",
    "email" : "bruno@gmail",
    "cpf" : 222
  }, {
    "idCliente" : 55,
    "nome" : "Carlos",
    "endereco" : "Rua A",
    "telefone" : "111111",
    "email" : "carlos@gmail",
    "cpf" : 333
  }, {
    "idCliente" : 56,
    "nome" : "Ana",
    "endereco" : "Rua B",
    "telefone" : "2222222",
    "email" : "ana@gmail",
    "cpf" : 111
  }, {
    "idCliente" : 57,
    "nome" : "Bruno",
    "endereco" : "Rua C",
    "telefone" : "3333333",
    "email" : "bruno@gmail",
    "cpf" : 222
  }, {
    "idCliente" : 58,
    "nome" : "Carlos",
    "endereco" : "Rua A",
    "telefone" : "111111",
    "email" : "carlos@gmail",
    "cpf" : 333
  }, {
    "idCliente" : 59,
    "nome" : "Ana",
    "endereco" : "Rua B",
    "telefone" : "2222222",
    "email" : "ana@gmail",
    "cpf" : 111
  }, {
    "idCliente" : 60,
    "nome" : "Bruno",
    "endereco" : "Rua C",
    "telefone" : "3333333",
    "email" : "bruno@gmail",
    "cpf" : 222
  }, {
    "idCliente" : 61,
    "nome" : "Carlos",
    "endereco" : "Rua A",
    "telefone" : "111111",
    "email" : "carlos@gmail",
    "cpf" : 333
  }, {
    "idCliente" : 62,
    "nome" : "Ana",
    "endereco" : "Rua B",
    "telefone" : "2222222",
    "email" : "ana@gmail",
    "cpf" : 111
  }, {
    "idCliente" : 63,
    "nome" : "Bruno",
    "endereco" : "Rua C",
    "telefone" : "3333333",
    "email" : "bruno@gmail",
    "cpf" : 222
  }, {
    "idCliente" : 64,
    "nome" : "Carlos",
    "endereco" : "Rua A",
    "telefone" : "111111",
    "email" : "carlos@gmail",
    "cpf" : 333
  }, {
    "idCliente" : 65,
    "nome" : "Ana",
    "endereco" : "Rua B",
    "telefone" : "2222222",
    "email" : "ana@gmail",
    "cpf" : 111
  }, {
    "idCliente" : 66,
    "nome" : "Bruno",
    "endereco" : "Rua C",
    "telefone" : "3333333",
    "email" : "bruno@gmail",
    "cpf" : 222
  }, {
    "idCliente" : 67,
    "nome" : "Carlos",
    "endereco" : "Rua A",
    "telefone" : "111111",
    "email" : "carlos@gmail",
    "cpf" : 333
  }, {
    "idCliente" : 68,
    "nome" : "Ana",
    "endereco" : "Rua B",
    "telefone" : "2222222",
    "email" : "ana@gmail",
    "cpf" : 111
  }, {
    "idCliente" : 69,
    "nome" : "Bruno",
    "endereco" : "Rua C",
    "telefone" : "3333333",
    "email" : "bruno@gmail",
    "cpf" : 222
  } ]
}